envmgr_healthchecks/__init__.py
envmgr_healthchecks/api/__init__.py
envmgr_healthchecks/api/consul/__init__.py
envmgr_healthchecks/api/consul/consul_api.py
envmgr_healthchecks/api/consul/consul_config.py
envmgr_healthchecks/health_checks/__init__.py
envmgr_healthchecks/health_checks/consul_health_check.py
envmgr_healthchecks/health_checks/health_check.py
envmgr_healthchecks/health_checks/health_check_errors.py
envmgr_healthchecks/health_checks/sensu_heath_check.py
envmgr_healthchecks-0.0.4.dist-info/DESCRIPTION.rst
envmgr_healthchecks-0.0.4.dist-info/METADATA
envmgr_healthchecks-0.0.4.dist-info/RECORD
envmgr_healthchecks-0.0.4.dist-info/WHEEL
envmgr_healthchecks-0.0.4.dist-info/metadata.json
envmgr_healthchecks-0.0.4.dist-info/top_level.txt
