Metadata-Version: 2.0
Name: envmgr-healthchecks
Version: 0.0.4
Summary: Consul Deployment Agent - Health Checks
Home-page: https://github.com/trainline/healthcheck-registrar
Author: Trainline Platform Development
Author-email: platform.development@thetrainline.com
License: Apache 2.0
Platform: UNKNOWN
Requires-Dist: appdirs
Requires-Dist: docopt
Requires-Dist: envmgr-lib (==0.2.1)
Requires-Dist: future
Requires-Dist: progressbar2
Requires-Dist: semver
Requires-Dist: simplejson
Requires-Dist: tabulate
